django_icekit-0.17.2.dist-info/DESCRIPTION.rst
django_icekit-0.17.2.dist-info/METADATA
django_icekit-0.17.2.dist-info/RECORD
django_icekit-0.17.2.dist-info/WHEEL
django_icekit-0.17.2.dist-info/metadata.json
django_icekit-0.17.2.dist-info/top_level.txt
icekit/__init__.py
icekit/abstract_models.py
icekit/admin.py
icekit/admin_forms.py
icekit/admin_mixins.py
icekit/apps.py
icekit/appsettings.py
icekit/fields.py
icekit/managers.py
icekit/middleware.py
icekit/mixins.py
icekit/models.py
icekit/search_indexes.py
icekit/tasks.py
icekit/validators.py
icekit/views.py
icekit/admin_tools/__init__.py
icekit/admin_tools/apps.py
icekit/admin_tools/filters.py
icekit/admin_tools/forms.py
icekit/admin_tools/mixins.py
icekit/admin_tools/models.py
icekit/admin_tools/polymorphic.py
icekit/admin_tools/previews.py
icekit/admin_tools/utils.py
icekit/admin_tools/widgets.py
icekit/admin_tools/static/admin/css/icekit_dashboard.less
icekit/admin_tools/static/admin/css/override.less
icekit/admin_tools/static/admin/css/preview-field-admin.css
icekit/admin_tools/static/admin/img/header-brand.png
icekit/admin_tools/static/admin/js/fluent_layouts.js
icekit/admin_tools/static/admin/js/icekit_dashboard.js
icekit/admin_tools/static/admin/js/jquery.matchHeight.js
icekit/admin_tools/static/admin/js/preview-field-admin.js
icekit/admin_tools/templates/admin/base_site.html
icekit/admin_tools/templates/admin/fluent_layouts_change_form.html
icekit/admin_tools/templates/admin/index.html
icekit/admin_tools/templates/admin/password_reset_email.html
icekit/admin_tools/templates/admin/dashboard_widgets/_widget.html
icekit/admin_tools/templates/admin/dashboard_widgets/_widget_assigned_to_link.html
icekit/admin_tools/templates/admin/dashboard_widgets/_widget_recent_actions_link.html
icekit/admin_tools/templates/admin/dashboard_widgets/assigned_to_me.html
icekit/admin_tools/templates/admin/dashboard_widgets/featured_app.html
icekit/admin_tools/templates/admin/dashboard_widgets/recent_actions.html
icekit/admin_tools/templates/admin/polymorphic_tree/jstree_list_results.html
icekit/admin_tools/templates/icekit/admin/fluent_layouts_change_form.html
icekit/admin_tools/templatetags/__init__.py
