Metadata-Version: 2.0
Name: django-icekit
Version: 0.17.2
Summary: A modular content CMS by Interaction Consortium.
Home-page: https://github.com/ic-labs/django-icekit
Author: Interaction Consortium
Author-email: studio@interaction.net.au
License: MIT
Platform: UNKNOWN
Requires-Dist: Pillow (>=4)
Requires-Dist: django-any-urlfield
Requires-Dist: django-app-namespace-template-loader
Requires-Dist: django-bootstrap3
Requires-Dist: django-compressor
Requires-Dist: django-el-pagination
Requires-Dist: django-extensions
Requires-Dist: django-fluent-contents (>=1.1.9)
Requires-Dist: django-fluent-pages (!=1.1)
Requires-Dist: django-model-settings
Requires-Dist: django-mptt
Requires-Dist: django-multiurl
Requires-Dist: django-object-actions (>=0.7)
Requires-Dist: django-polymorphic (!=1.0.1,>=0.8,!=1)
Requires-Dist: django-wysiwyg
Requires-Dist: html5lib (==0.999)
Requires-Dist: nltk
Requires-Dist: pip-tools
Requires-Dist: requests
Requires-Dist: unidecode
Provides-Extra: api
Requires-Dist: djangorestframework; extra == 'api'
Provides-Extra: brightcove
Requires-Dist: django-brightcove; extra == 'brightcove'
Provides-Extra: dev
Requires-Dist: Werkzeug; extra == 'dev'
Requires-Dist: django-debug-toolbar; extra == 'dev'
Requires-Dist: ipdb; extra == 'dev'
Requires-Dist: ipython (<5); extra == 'dev'
Requires-Dist: mkdocs; extra == 'dev'
Provides-Extra: django18
Requires-Dist: Django (>=1.8,<1.9); extra == 'django18'
Provides-Extra: docs
Requires-Dist: recommonmark; extra == 'docs'
Requires-Dist: sphinx; extra == 'docs'
Requires-Dist: sphinx-autobuild; extra == 'docs'
Provides-Extra: forms
Requires-Dist: django-forms-builder; extra == 'forms'
Provides-Extra: glamkit
Requires-Dist: glamkit-collections (>=0.35); extra == 'glamkit'
Requires-Dist: glamkit-sponsors; extra == 'glamkit'
Requires-Dist: icekit-events; extra == 'glamkit'
Requires-Dist: icekit-press-releases (>=0.81); extra == 'glamkit'
Provides-Extra: project
Requires-Dist: ConcurrentLogHandler; extra == 'project'
Requires-Dist: Jinja2; extra == 'project'
Requires-Dist: boto3; extra == 'project'
Requires-Dist: celery[redis] (<4.0); extra == 'project'
Requires-Dist: django-celery; extra == 'project'
Requires-Dist: django-celery-email; extra == 'project'
Requires-Dist: django-countries; extra == 'project'
Requires-Dist: django-extensions; extra == 'project'
Requires-Dist: django-flat-theme (<1.1.3); extra == 'project'
Requires-Dist: django-fluent-contents[markupoembeditemtext]; extra == 'project'
Requires-Dist: django-fluent-pages[redirectnodereversion]; extra == 'project'
Requires-Dist: django-master-password; extra == 'project'
Requires-Dist: django-polymorphic-auth; extra == 'project'
Requires-Dist: django-post-office; extra == 'project'
Requires-Dist: django-redis; extra == 'project'
Requires-Dist: django-reversion (<1.10,>=1.9.3); extra == 'project'
Requires-Dist: django-storages; extra == 'project'
Requires-Dist: django-test-without-migrations; extra == 'project'
Requires-Dist: django-timezone; extra == 'project'
Requires-Dist: docutils; extra == 'project'
Requires-Dist: easy-thumbnails; extra == 'project'
Requires-Dist: flower; extra == 'project'
Requires-Dist: gunicorn; extra == 'project'
Requires-Dist: icekit-notifications; extra == 'project'
Requires-Dist: ixc-django-compressor; extra == 'project'
Requires-Dist: ixc-whitenoise; extra == 'project'
Requires-Dist: psycopg2; extra == 'project'
Requires-Dist: python-redis-lock[django]; extra == 'project'
Requires-Dist: pytz; extra == 'project'
Requires-Dist: raven; extra == 'project'
Requires-Dist: supervisor; extra == 'project'
Provides-Extra: search
Requires-Dist: django-fluent-pages[fluentpage,flatpage]; extra == 'search'
Requires-Dist: django-haystack; extra == 'search'
Requires-Dist: elasticsearch; extra == 'search'
Requires-Dist: elasticstack; extra == 'search'
Provides-Extra: test
Requires-Dist: WebTest; extra == 'test'
Requires-Dist: celery[redis] (==3.1.24); extra == 'test'
Requires-Dist: coverage; extra == 'test'
Requires-Dist: coveralls; extra == 'test'
Requires-Dist: django-dynamic-fixture; extra == 'test'
Requires-Dist: django-nose; extra == 'test'
Requires-Dist: django-webtest; extra == 'test'
Requires-Dist: djangorestframework; extra == 'test'
Requires-Dist: micawber; extra == 'test'
Requires-Dist: mock; extra == 'test'
Requires-Dist: nose-progressive; extra == 'test'
Requires-Dist: psycopg2; extra == 'test'
